Metadata-Version: 2.1
Name: pdf-bookmark-manager-mbreac
Version: 0.9
Summary: Simple GTK+ app for creating or editing pdf bookmarks/table of contents, with optional zathura integration'
Home-page: https://github.com/mbrea-c/pdf-bookmark-manager
Author: Manuel Brea Carreras
Author-email: m.brea.carreras@gmail.com
License: UNKNOWN
Platform: UNKNOWN
Requires-Python: >=3.6
Requires-Dist: dbus-python (>=1.2.16)
Requires-Dist: PyGObject (>=3.40.1)
